GCD Implementation using FSM/A5Q1_gcd.v
module gcd (
  input [7:0] inX, inY,
  output [7:0] out
);

  reg [7:0] X, Y, out, swap;
  integer done;

  always @(*) begin
    done = 0;
    X = inX; Y = inY;
    while ( !done )
    begin
      if ( X < Y ) begin
        swap = X;
        X = Y;
        Y = swap;
      end
      else if ( Y != 0 )
        X = X - Y;
      else
        done = 1;
    end
  out = X;
  end

endmodule

GCD Implementation using FSM/A5Q1_tb.v
`include "A5Q1_gcd.v"
module gcd_tb;
reg [7:0] x,y;
wire[7:0] o;
initial begin
    $dumpfile("gcd_tb.vcd");
    $dumpvars(0,gcd_tb);
end
gcd c(.inX(x),.inY(y),.out(o));

initial begin
    x=8'd60;y=8'd65;
    #5
    $display("x = %b , y = %b  , gcd = %b", x,y,o);
    x=8'd160;y=8'd203;
    #5
    $display("x = %b , y = %b  , gcd = %b", x,y,o);
    x=8'd58;y=8'd120;
    #5
    $display("x = %b , y = %b  , gcd = %b", x,y,o);
    x=8'd61;y=8'd244;
    #5
    $display("x = %b , y = %b  , gcd = %b", x,y,o);
    x=8'd124;y=8'd48;
    #5
    $display("x = %b , y = %b  , gcd = %b", x,y,o);
    x=8'd63;y=8'd45;
    #5
    $display("x = %b , y = %b  , gcd = %b", x,y,o);
    x=8'd79;y=8'd165;
    #5
    $display("x = %b , y = %b  , gcd = %b", x,y,o);
    x=8'd88;y=8'd77;
    #5
    $display("x = %b , y = %b  , gcd = %b", x,y,o);
    x=8'd56;y=8'd80;
    #5
    $display("x = %b , y = %b  , gcd = %b", x,y,o);
    x=8'd22;y=8'd22;
    #5
    $display("x = %b , y = %b  , gcd = %b", x,y,o);
    x=8'd84;y=8'd224;
    #5
    $display("x = %b , y = %b  , gcd = %b", x,y,o);
    x=8'd26;y=8'd49;
    #5
    $display("x = %b , y = %b  , gcd = %b", x,y,o);
    x=8'd109;y=8'd73;
    #5
    $display("x = %b , y = %b  , gcd = %b", x,y,o);
    x=8'd132;y=8'd70;
    #5
    $display("x = %b , y = %b  , gcd = %b", x,y,o);
    x=8'd54;y=8'd13;
    #5
    $display("x = %b , y = %b  , gcd = %b", x,y,o);
end

endmodule

GCD Implementation using FSM/gcd_tb.vcd
$date
	Wed Mar 23 23:24:02 2022
$end
$version
	Icarus Verilog
$end
$timescale
	1s
$end
$scope module gcd_tb $end
$var wire 8 ! o [7:0] $end
$var reg 8 " x [7:0] $end
$var reg 8 # y [7:0] $end
$scope module c $end
$var wire 8 $ inX [7:0] $end
$var wire 8 % inY [7:0] $end
$var reg 8 & X [7:0] $end
$var reg 8 ' Y [7:0] $end
$var reg 8 ( out [7:0] $end
$var reg 8 ) swap [7:0] $end
$var integer 32 * done [31:0] $end
$upscope $end
$upscope $end
$enddefinitions $end
#0
$dumpvars
b1 *
b0 )
b101 (
b0 '
b101 &
b1000001 %
b111100 $
b1000001 #
b111100 "
b101 !
$end
#5
b1 !
b1 (
b0 )
b0 '
b1 &
b1 *
b11001011 #
b11001011 %
b10100000 "
b10100000 $
#10
b10 !
b10 (
b0 )
b0 '
b10 &
b1 *
b1111000 #
b1111000 %
b111010 "
b111010 $
#15
b111101 !
b111101 (
b0 )
b0 '
b111101 &
b1 *
b11110100 #
b11110100 %
b111101 "
b111101 $
#20
b100 !
b100 (
b0 )
b0 '
b100 &
b1 *
b110000 #
b110000 %
b1111100 "
b1111100 $
#25
b1001 !
b1001 (
b0 )
b0 '
b1001 &
b1 *
b101101 #
b101101 %
b111111 "
b111111 $
#30
b1 !
b1 (
b0 )
b0 '
b1 &
b1 *
b10100101 #
b10100101 %
b1001111 "
b1001111 $
#35
b1011 !
b1011 (
b0 )
b0 '
b1011 &
b1 *
b1001101 #
b1001101 %
b1011000 "
b1011000 $
#40
b1000 !
b1000 (
b0 )
b0 '
b1000 &
b1 *
b1010000 #
b1010000 %
b111000 "
b111000 $
#45
b10110 !
b10110 (
b0 '
b10110 &
b1 *
b10110 #
b10110 %
b10110 "
b10110 $
#50
b11100 !
b11100 (
b0 )
b0 '
b11100 &
b1 *
b11100000 #
b11100000 %
b1010100 "
b1010100 $
#55
b1 !
b1 (
b0 )
b0 '
b1 &
b1 *
b110001 #
b110001 %
b11010 "
b11010 $
#60
b0 )
b0 '
b1 &
b1 *
b1001001 #
b1001001 %
b1101101 "
b1101101 $
#65
b10 !
b10 (
b0 )
b0 '
b10 &
b1 *
b1000110 #
b1000110 %
b10000100 "
b10000100 $
#70
b1 !
b1 (
b0 )
b0 '
b1 &
b1 *
b1101 #
b1101 %
b110110 "
b110110 $
